odoo/addons/ssi_transaction_ready_mixin/README.rst
odoo/addons/ssi_transaction_ready_mixin/__init__.py
odoo/addons/ssi_transaction_ready_mixin/__manifest__.py
odoo/addons/ssi_transaction_ready_mixin/i18n/ssi_transaction_ready_mixin.pot
odoo/addons/ssi_transaction_ready_mixin/models/__init__.py
odoo/addons/ssi_transaction_ready_mixin/models/mixin_transaction_ready.py
odoo/addons/ssi_transaction_ready_mixin/static/description/icon.png
odoo/addons/ssi_transaction_ready_mixin/templates/mixin_transaction_ready_templates.xml
odoo14_addon_ssi_transaction_ready_mixin-14.0.1.11.1.dist-info/METADATA
odoo14_addon_ssi_transaction_ready_mixin-14.0.1.11.1.dist-info/WHEEL
odoo14_addon_ssi_transaction_ready_mixin-14.0.1.11.1.dist-info/top_level.txt
odoo14_addon_ssi_transaction_ready_mixin-14.0.1.11.1.dist-info/RECORD
